README.txt
setup.py
coopr/__init__.py
coopr.plugins.egg-info/PKG-INFO
coopr.plugins.egg-info/SOURCES.txt
coopr.plugins.egg-info/dependency_links.txt
coopr.plugins.egg-info/entry_points.txt
coopr.plugins.egg-info/namespace_packages.txt
coopr.plugins.egg-info/top_level.txt
coopr/plugins/__init__.py
coopr/plugins/converter/__init__.py
coopr/plugins/converter/ampl.py
coopr/plugins/converter/glpsol.py
coopr/plugins/converter/pico.py
coopr/plugins/converter/pyomo.py
coopr/plugins/smanager/__init__.py
coopr/plugins/smanager/phpyro.py
coopr/plugins/smanager/pyro.py
coopr/plugins/solvers/ASL.py
coopr/plugins/solvers/CBCplugin.py
coopr/plugins/solvers/CPLEX.py
coopr/plugins/solvers/CPLEXDirect.py
coopr/plugins/solvers/GLPK.py
coopr/plugins/solvers/GLPK_old.py
coopr/plugins/solvers/GUROBI.py
coopr/plugins/solvers/GUROBI_RUN.py
coopr/plugins/solvers/PICO.py
coopr/plugins/solvers/SCIPAMPL.py
coopr/plugins/solvers/XPRESS.py
coopr/plugins/solvers/__init__.py
coopr/plugins/solvers/glpk_direct.py
coopr/plugins/solvers/gurobi_direct.py
coopr/plugins/solvers/mockmip.py
coopr/plugins/solvers/ps.py
coopr/plugins/solvers/wrappers.py
coopr/plugins/testdriver/__init__.py
coopr/plugins/testdriver/mip.py
coopr/plugins/testdriver/pyomo.py
coopr/plugins/tests/__init__.py
coopr/plugins/tests/mip/__init__.py
coopr/plugins/tests/mip/model.py
coopr/plugins/tests/mip/test_asl.py
coopr/plugins/tests/mip/test_convert.py
coopr/plugins/tests/mip/test_factory.py
coopr/plugins/tests/mip/test_ipopt.py
coopr/plugins/tests/mip/test_mip.py
coopr/plugins/tests/mip/test_solver.py
coopr/plugins/tests/pickling/__init__.py
coopr/plugins/tests/pickling/test_pickle.py
coopr/plugins/tests/pickling/trivial_model.py